nbss_upload.py
pb_nbss_upload-0.1.dist-info/LICENSE
pb_nbss_upload-0.1.dist-info/METADATA
pb_nbss_upload-0.1.dist-info/WHEEL
pb_nbss_upload-0.1.dist-info/entry_points.txt
pb_nbss_upload-0.1.dist-info/top_level.txt
pb_nbss_upload-0.1.dist-info/RECORD
