Metadata-Version: 2.1
Name: pb-nbss-upload
Version: 0.1
Summary: Upload notebooks to Private cloud
Home-page: http://127.0.0.1:8000
Author: AbhishekJadhav-RamandeepMakkar
Author-email: abhicjadhav@gmail.com
License: 3-clause BSD
Platform: any
License-File: LICENSE
Requires-Dist: requests
